hanzo_tools/__init__.py
hanzo_tools/core/__init__.py
hanzo_tools/core/base.py
hanzo_tools/core/context.py
hanzo_tools/core/decorators.py
hanzo_tools/core/permissions.py
hanzo_tools/core/types.py
hanzo_tools/core/validation.py
hanzo_tools-0.3.0.dist-info/METADATA
hanzo_tools-0.3.0.dist-info/WHEEL
hanzo_tools-0.3.0.dist-info/top_level.txt
hanzo_tools-0.3.0.dist-info/RECORD
